himile_model_middleware/__init__.py
himile_model_middleware/db_pool.py
himile_model_middleware/hello.py
himile_model_middleware-0.2.0.dist-info/METADATA
himile_model_middleware-0.2.0.dist-info/WHEEL
himile_model_middleware-0.2.0.dist-info/top_level.txt
himile_model_middleware-0.2.0.dist-info/RECORD
