Metadata-Version: 2.4
Name: himile_model_middleware
Version: 0.2.0
Summary: A VLLM middleware package
Author-email: qhw <20244111@himile.net>
Requires-Python: >=3.10
Requires-Dist: aiomysql>=0.2.0
Requires-Dist: vllm>=0.8.4
Requires-Dist: PyYAML>=6.0.2
Requires-Dist: starlette>=0.46.2
Requires-Dist: fastapi>=0.115.12
